<annotation>
	<folder>JPEGImages</folder>
	<filename>2753.jpg</filename>
	<path>C:\Users\郗康\Desktop\VOC2007\JPEGImages\2753.jpg</path>
	<source>
		<database>Unknown</database>
	</source>
	<size>
		<width>1080</width>
		<height>1920</height>
		<depth>3</depth>
	</size>
	<segmented>0</segmented>
	<object>
		<name>Image</name>
		<pose>Unspecified</pose>
		<truncated>0</truncated>
		<difficult>0</difficult>
		<bndbox>
			<xmin>5</xmin>
			<ymin>69</ymin>
			<xmax>1077</xmax>
			<ymax>750</ymax>
		</bndbox>
	</object>
	<object>
		<name>EditText</name>
		<pose>Unspecified</pose>
		<truncated>0</truncated>
		<difficult>0</difficult>
		<bndbox>
			<xmin>170</xmin>
			<ymin>960</ymin>
			<xmax>915</xmax>
			<ymax>1053</ymax>
		</bndbox>
	</object>
	<object>
		<name>EditText</name>
		<pose>Unspecified</pose>
		<truncated>0</truncated>
		<difficult>0</difficult>
		<bndbox>
			<xmin>177</xmin>
			<ymin>1071</ymin>
			<xmax>908</xmax>
			<ymax>1171</ymax>
		</bndbox>
	</object>
	<object>
		<name>Text</name>
		<pose>Unspecified</pose>
		<truncated>0</truncated>
		<difficult>0</difficult>
		<bndbox>
			<xmin>170</xmin>
			<ymin>1201</ymin>
			<xmax>461</xmax>
			<ymax>1248</ymax>
		</bndbox>
	</object>
	<object>
		<name>Text</name>
		<pose>Unspecified</pose>
		<truncated>0</truncated>
		<difficult>0</difficult>
		<bndbox>
			<xmin>262</xmin>
			<ymin>1639</ymin>
			<xmax>818</xmax>
			<ymax>1678</ymax>
		</bndbox>
	</object>
	<object>
		<name>Switch</name>
		<pose>Unspecified</pose>
		<truncated>0</truncated>
		<difficult>0</difficult>
		<bndbox>
			<xmin>609</xmin>
			<ymin>1189</ymin>
			<xmax>909</xmax>
			<ymax>1268</ymax>
		</bndbox>
	</object>
	<object>
		<name>TextButton</name>
		<pose>Unspecified</pose>
		<truncated>0</truncated>
		<difficult>0</difficult>
		<bndbox>
			<xmin>171</xmin>
			<ymin>1275</ymin>
			<xmax>911</xmax>
			<ymax>1403</ymax>
		</bndbox>
	</object>
	<object>
		<name>Text</name>
		<pose>Unspecified</pose>
		<truncated>0</truncated>
		<difficult>0</difficult>
		<bndbox>
			<xmin>91</xmin>
			<ymin>1709</ymin>
			<xmax>265</xmax>
			<ymax>1765</ymax>
		</bndbox>
	</object>
	<object>
		<name>Text</name>
		<pose>Unspecified</pose>
		<truncated>0</truncated>
		<difficult>0</difficult>
		<bndbox>
			<xmin>411</xmin>
			<ymin>1713</ymin>
			<xmax>649</xmax>
			<ymax>1766</ymax>
		</bndbox>
	</object>
	<object>
		<name>Text</name>
		<pose>Unspecified</pose>
		<truncated>0</truncated>
		<difficult>0</difficult>
		<bndbox>
			<xmin>826</xmin>
			<ymin>1724</ymin>
			<xmax>977</xmax>
			<ymax>1768</ymax>
		</bndbox>
	</object>
</annotation>
